inoyb/__init__.py
inoyb/cli.py
inoyb/config/__init__.py
inoyb/config/manager.py
inoyb/config/settings.py
inoyb/core/__init__.py
inoyb/core/service.py
inoyb/docker/__init__.py
inoyb/docker/builder.py
inoyb/docker/config.py
inoyb/docker/manager.py
inoyb/docker/templates/dockerfile-gpu.template
inoyb/docker/templates/dockerfile.template
inoyb/example/gogogo.py
inoyb/example/model/test_model.py
inoyb/execution/__init__.py
inoyb/execution/executor.py
inoyb/files/__init__.py
inoyb/files/handler.py
inoyb/runner/__init__.py
inoyb/runner/container.py
inoyb/runner/local.py
inoyb/static/favicon.ico
inoyb/ui/__init__.py
inoyb/ui/components.py
inoyb/utils/isolated_executor.py
inoyb/utils/logger.py
inoyb/utils/preview.py
inoyb-1.1.21.dist-info/METADATA
inoyb-1.1.21.dist-info/WHEEL
inoyb-1.1.21.dist-info/entry_points.txt
inoyb-1.1.21.dist-info/top_level.txt
inoyb-1.1.21.dist-info/RECORD
