Metadata-Version: 2.4
Name: inoyb
Version: 1.1.21
Summary: 极其友好的地理空间AI模型服务框架 - Docker化部署，支持Gradio界面
Home-page: https://github.com/ldichen/It-is-none-of-your-business
Author: DiChen
Author-email: DiChen <ldicccccc@gmail.com>
License: MIT
Project-URL: Homepage, https://github.com/ldichen/It-is-none-of-your-business
Project-URL: Repository, https://github.com/ldichen/It-is-none-of-your-business
Project-URL: Documentation, https://github.com/ldichen/It-is-none-of-your-business#readme
Project-URL: Bug Reports, https://github.com/ldichen/It-is-none-of-your-business/issues
Project-URL: Changelog, https://github.com/ldichen/It-is-none-of-your-business/releases
Keywords: gradio,model,service,framework,ml,ai,docker,geospatial,rasterio,gdal,openGMS
Classifier: Development Status :: 4 - Beta
Classifier: Intended Audience :: Developers
Classifier: Topic :: Software Development :: Libraries :: Python Modules
Classifier: License :: OSI Approved :: MIT License
Classifier: Programming Language :: Python :: 3
Classifier: Programming Language :: Python :: 3.8
Classifier: Programming Language :: Python :: 3.9
Classifier: Programming Language :: Python :: 3.10
Classifier: Programming Language :: Python :: 3.11
Classifier: Programming Language :: Python :: 3.12
Classifier: Programming Language :: Python :: 3.13
Requires-Python: >=3.8
Requires-Dist: gradio>=4.0.0
Requires-Dist: rasterio>=1.3.0
Requires-Dist: matplotlib<4.0.0,>=3.5.0
Requires-Dist: Pillow>=8.0.0
Requires-Dist: docker>=7.0.0
Requires-Dist: pathlib2>=2.3.0; python_version < "3.8"
Provides-Extra: dev
Requires-Dist: pytest>=7.0.0; extra == "dev"
Requires-Dist: black>=22.0.0; extra == "dev"
Requires-Dist: flake8>=4.0.0; extra == "dev"
Requires-Dist: mypy>=0.950; extra == "dev"
Requires-Dist: twine>=4.0.0; extra == "dev"
Requires-Dist: build>=0.8.0; extra == "dev"
Provides-Extra: gpu
Requires-Dist: torch>=1.12.0; extra == "gpu"
Requires-Dist: torchvision>=0.13.0; extra == "gpu"
Requires-Dist: torchaudio>=0.12.0; extra == "gpu"
Dynamic: author
Dynamic: home-page
Dynamic: requires-python
